enedis_data_connect/__init__.py
enedis_data_connect/enedis_client.py
enedis_data_connect/utils.py
enedis_data_connect-1.1.0.dist-info/LICENSE
enedis_data_connect-1.1.0.dist-info/METADATA
enedis_data_connect-1.1.0.dist-info/WHEEL
enedis_data_connect-1.1.0.dist-info/top_level.txt
enedis_data_connect-1.1.0.dist-info/RECORD
