Metadata-Version: 2.1
Name: enedis_data_connect
Version: 1.1.0
Summary: Enedis data connect client
Home-page: https://github.com/infodavide/enedis_data_connect
Author: David R
Author-email: contact@infodavid.org
License: GNU GENERAL PUBLIC LICENSE
License-File: LICENSE
